cdk_datalake_constructs/__init__.py
cdk_datalake_constructs/py.typed
cdk_datalake_constructs/_jsii/__init__.py
cdk_datalake_constructs/_jsii/cdk-datalake-constructs@0.0.64.jsii.tgz
cdk_datalake_constructs-0.0.64.dist-info/LICENSE
cdk_datalake_constructs-0.0.64.dist-info/METADATA
cdk_datalake_constructs-0.0.64.dist-info/WHEEL
cdk_datalake_constructs-0.0.64.dist-info/top_level.txt
cdk_datalake_constructs-0.0.64.dist-info/RECORD
