Metadata-Version: 2.1
Name: cdk-datalake-constructs
Version: 0.0.64
Summary: AWS CDK Constructs that can be used to create datalakes/meshes and more
Home-page: https://github.com/randyridgley/cdk-datalake-constructs.git
Author: Randy Ridgley<randy.ridgley@gmail.com>
License: MIT
Project-URL: Source, https://github.com/randyridgley/cdk-datalake-constructs.git
Classifier: Intended Audience :: Developers
Classifier: Operating System :: OS Independent
Classifier: Programming Language :: JavaScript
Classifier: Programming Language :: Python :: 3 :: Only
Classifier: Programming Language :: Python :: 3.7
Classifier: Programming Language :: Python :: 3.8
Classifier: Programming Language :: Python :: 3.9
Classifier: Programming Language :: Python :: 3.10
Classifier: Typing :: Typed
Classifier: Development Status :: 5 - Production/Stable
Classifier: License :: OSI Approved
Requires-Python: ~=3.7
License-File: LICENSE
Requires-Dist: aws-cdk-lib (<3.0.0,>=2.13.0)
Requires-Dist: aws-cdk.aws-glue-alpha (<3.0.0,>=2.47.0.a0)
Requires-Dist: aws-cdk.aws-lambda-python-alpha (<3.0.0,>=2.47.0.a0)
Requires-Dist: constructs (<11.0.0,>=10.0.5)
Requires-Dist: jsii (<2.0.0,>=1.70.0)
Requires-Dist: publication (>=0.0.3)
Requires-Dist: typeguard (~=2.13.3)
